bombcell/__init__.py
bombcell/bombcell.py
bombcell/bombcell_matlab_script_template.py
breg_util/__init__.py
breg_util/brainreg_command_line_util.py
pipelinerz/__init__.py
pipelinerz/process_data_gui.py
pp_slurm/__init__.py
pp_slurm/hpc.py
pp_slurm/slurm.py
pp_slurm/slurm_functions.py
pp_slurm/slurm_interfaces/__init__.py
pp_slurm/slurm_interfaces/bombcell.py
pp_slurm/slurm_interfaces/brainreg.py
pp_slurm/slurm_interfaces/sort.py
pp_slurm/slurm_interfaces/track_mouse_dlc.py
pipelinerz-0.1.2.dist-info/LICENSE
pipelinerz-0.1.2.dist-info/METADATA
pipelinerz-0.1.2.dist-info/WHEEL
pipelinerz-0.1.2.dist-info/entry_points.txt
pipelinerz-0.1.2.dist-info/top_level.txt
pipelinerz-0.1.2.dist-info/RECORD
